<?xml version="1.0" encoding="utf-8" ?><dwsync><file name="9-174.pdf" server="80.80.233.51" local="3562527600" remote="3562527600" Dst="-1" /><file name="6-83.pdf" server="80.80.233.51" local="3562527600" remote="3562527600" Dst="-1" /><file name="4-171.pdf" server="80.80.233.51" local="3562527600" remote="3562527600" Dst="-1" /><file name="3-234.pdf" server="80.80.233.51" local="3562527600" remote="3562527600" Dst="-1" /><file name="2-139.pdf" server="80.80.233.51" local="3562527600" remote="3562527600" Dst="-1" /><file name="1-54.pdf" server="80.80.233.51" local="3562527600" remote="3562527600" Dst="-1" /><file name="08-2006-05.pdf" server="80.80.233.51" local="3562527600" remote="3562527600" Dst="-1" /><file name="07-2006-04.pdf" server="80.80.233.51" local="3562527600" remote="3562527600" Dst="-1" /><file name="05-2006-02.pdf" server="80.80.233.51" local="3562527600" remote="3562527600" Dst="-1" /></dwsync>